setup.py
distributions_prorpp/Binomialdistribution.py
distributions_prorpp/Gaussiandistribution.py
distributions_prorpp/Generaldistribution.py
distributions_prorpp/__init__.py
distributions_prorpp.egg-info/PKG-INFO
distributions_prorpp.egg-info/SOURCES.txt
distributions_prorpp.egg-info/dependency_links.txt
distributions_prorpp.egg-info/not-zip-safe
distributions_prorpp.egg-info/top_level.txt