Metadata-Version: 1.0
Name: distributions-prorpp
Version: 0.441
Summary: Gaussian distributions
Home-page: UNKNOWN
Author:  Hassan Algizani 
Author-email: Hassan.jezo@outlook.com
License: UNKNOWN
Platform: UNKNOWN
